{
  "content": [
    {
      "attrs": {
        "level": 1
      },
      "content": [
        {
          "text": "Native editor round-trip acceptance",
          "type": "text"
        }
      ],
      "type": "heading"
    },
    {
      "content": [
        {
          "text": "This page was downloaded, edited as local Confluence storage, preflight-rendered by Confluence, uploaded, and verified through the API and authenticated browser.",
          "type": "text"
        }
      ],
      "type": "paragraph"
    },
    {
      "attrs": {
        "level": 2
      },
      "content": [
        {
          "text": "Heading hierarchy",
          "type": "text"
        }
      ],
      "type": "heading"
    },
    {
      "attrs": {
        "level": 1
      },
      "content": [
        {
          "text": "Heading level 1 fixture",
          "type": "text"
        }
      ],
      "type": "heading"
    },
    {
      "attrs": {
        "level": 2
      },
      "content": [
        {
          "text": "Heading level 2 fixture",
          "type": "text"
        }
      ],
      "type": "heading"
    },
    {
      "attrs": {
        "level": 3
      },
      "content": [
        {
          "text": "Heading level 3 fixture",
          "type": "text"
        }
      ],
      "type": "heading"
    },
    {
      "attrs": {
        "level": 4
      },
      "content": [
        {
          "text": "Heading level 4 fixture",
          "type": "text"
        }
      ],
      "type": "heading"
    },
    {
      "attrs": {
        "level": 5
      },
      "content": [
        {
          "text": "Heading level 5 fixture",
          "type": "text"
        }
      ],
      "type": "heading"
    },
    {
      "attrs": {
        "level": 6
      },
      "content": [
        {
          "text": "Heading level 6 fixture",
          "type": "text"
        }
      ],
      "type": "heading"
    },
    {
      "attrs": {
        "level": 2
      },
      "content": [
        {
          "text": "Inline and block formatting",
          "type": "text"
        }
      ],
      "type": "heading"
    },
    {
      "content": [
        {
          "marks": [
            {
              "type": "strong"
            }
          ],
          "text": "Bold text",
          "type": "text"
        },
        {
          "text": ", ",
          "type": "text"
        },
        {
          "marks": [
            {
              "type": "em"
            }
          ],
          "text": "italic text",
          "type": "text"
        },
        {
          "text": ", ",
          "type": "text"
        },
        {
          "marks": [
            {
              "type": "underline"
            }
          ],
          "text": "underlined text",
          "type": "text"
        },
        {
          "text": ", ",
          "type": "text"
        },
        {
          "text": "struck text",
          "type": "text"
        },
        {
          "text": ", ",
          "type": "text"
        },
        {
          "marks": [
            {
              "attrs": {
                "type": "sup"
              },
              "type": "subsup"
            }
          ],
          "text": "superscript",
          "type": "text"
        },
        {
          "text": ", ",
          "type": "text"
        },
        {
          "marks": [
            {
              "attrs": {
                "type": "sub"
              },
              "type": "subsup"
            }
          ],
          "text": "subscript",
          "type": "text"
        },
        {
          "text": ", and ",
          "type": "text"
        },
        {
          "marks": [
            {
              "type": "code"
            }
          ],
          "text": "inline_code()",
          "type": "text"
        },
        {
          "text": ".",
          "type": "text"
        }
      ],
      "type": "paragraph"
    },
    {
      "content": [
        {
          "marks": [
            {
              "attrs": {
                "color": "#0052cc"
              },
              "type": "textColor"
            }
          ],
          "text": "Blue foreground",
          "type": "text"
        },
        {
          "text": ", ",
          "type": "text"
        },
        {
          "marks": [
            {
              "attrs": {
                "color": "#ffebe6"
              },
              "type": "backgroundColor"
            }
          ],
          "text": "red-tint highlight",
          "type": "text"
        },
        {
          "text": ", ",
          "type": "text"
        },
        {
          "text": "small text",
          "type": "text"
        },
        {
          "text": ", and ",
          "type": "text"
        },
        {
          "text": "big text",
          "type": "text"
        },
        {
          "text": ".",
          "type": "text"
        }
      ],
      "type": "paragraph"
    },
    {
      "content": [
        {
          "text": "Left-aligned acceptance marker",
          "type": "text"
        }
      ],
      "type": "paragraph"
    },
    {
      "content": [
        {
          "text": "Centered acceptance marker",
          "type": "text"
        }
      ],
      "marks": [
        {
          "attrs": {
            "align": "center"
          },
          "type": "alignment"
        }
      ],
      "type": "paragraph"
    },
    {
      "content": [
        {
          "text": "Right-aligned acceptance marker",
          "type": "text"
        }
      ],
      "marks": [
        {
          "attrs": {
            "align": "end"
          },
          "type": "alignment"
        }
      ],
      "type": "paragraph"
    },
    {
      "content": [
        {
          "content": [
            {
              "text": "Block quote preserved through storage conversion.",
              "type": "text"
            }
          ],
          "type": "paragraph"
        }
      ],
      "type": "blockquote"
    },
    {
      "content": [
        {
          "marks": [
            {
              "type": "code"
            }
          ],
          "text": "preformatted_line_1\npreformatted_line_2",
          "type": "text"
        }
      ],
      "type": "paragraph"
    },
    {
      "content": [
        {
          "text": "Line one",
          "type": "text"
        },
        {
          "type": "hardBreak"
        },
        {
          "text": "Line two after a soft break.",
          "type": "text"
        }
      ],
      "type": "paragraph"
    },
    {
      "type": "rule"
    },
    {
      "attrs": {
        "level": 2
      },
      "content": [
        {
          "text": "Lists and tasks",
          "type": "text"
        }
      ],
      "type": "heading"
    },
    {
      "content": [
        {
          "content": [
            {
              "content": [
                {
                  "text": "Unordered parent\n    ",
                  "type": "text"
                }
              ],
              "type": "paragraph"
            },
            {
              "content": [
                {
                  "content": [
                    {
                      "content": [
                        {
                          "text": "Nested unordered child",
                          "type": "text"
                        }
                      ],
                      "type": "paragraph"
                    }
                  ],
                  "type": "listItem"
                }
              ],
              "type": "bulletList"
            }
          ],
          "type": "listItem"
        },
        {
          "content": [
            {
              "content": [
                {
                  "text": "Second unordered item",
                  "type": "text"
                }
              ],
              "type": "paragraph"
            }
          ],
          "type": "listItem"
        }
      ],
      "type": "bulletList"
    },
    {
      "attrs": {
        "order": 1
      },
      "content": [
        {
          "content": [
            {
              "content": [
                {
                  "text": "Ordered parent\n    ",
                  "type": "text"
                }
              ],
              "type": "paragraph"
            },
            {
              "attrs": {
                "order": 1
              },
              "content": [
                {
                  "content": [
                    {
                      "content": [
                        {
                          "text": "Nested ordered child",
                          "type": "text"
                        }
                      ],
                      "type": "paragraph"
                    }
                  ],
                  "type": "listItem"
                }
              ],
              "type": "orderedList"
            }
          ],
          "type": "listItem"
        },
        {
          "content": [
            {
              "content": [
                {
                  "text": "Second ordered item",
                  "type": "text"
                }
              ],
              "type": "paragraph"
            }
          ],
          "type": "listItem"
        }
      ],
      "type": "orderedList"
    },
    {
      "attrs": {
        "localId": ""
      },
      "content": [
        {
          "attrs": {
            "localId": "native-incomplete-20260713",
            "state": "TODO"
          },
          "content": [
            {
              "text": "Review the native editor fixture with ",
              "type": "text"
            },
            {
              "attrs": {
                "id": "70121:6ec7fd06-929c-4771-add0-ec012097b466",
                "text": "@Gerardo Jorge Villarroel González"
              },
              "type": "mention"
            },
            {
              "text": " by ",
              "type": "text"
            },
            {
              "attrs": {
                "timestamp": "1784505600000"
              },
              "type": "date"
            }
          ],
          "type": "taskItem"
        },
        {
          "attrs": {
            "localId": "native-complete-20260713",
            "state": "DONE"
          },
          "content": [
            {
              "text": "Preflight the local storage representation",
              "type": "text"
            }
          ],
          "type": "taskItem"
        }
      ],
      "type": "taskList"
    },
    {
      "attrs": {
        "level": 2
      },
      "content": [
        {
          "text": "Rich table",
          "type": "text"
        }
      ],
      "type": "heading"
    },
    {
      "attrs": {
        "layout": "wide"
      },
      "content": [
        {
          "content": [
            {
              "attrs": {
                "colspan": 3,
                "rowspan": 1
              },
              "content": [
                {
                  "content": [
                    {
                      "text": "Native editor verification matrix",
                      "type": "text"
                    }
                  ],
                  "type": "paragraph"
                }
              ],
              "type": "tableHeader"
            }
          ],
          "type": "tableRow"
        },
        {
          "content": [
            {
              "attrs": {
                "colspan": 1,
                "rowspan": 1
              },
              "content": [
                {
                  "content": [
                    {
                      "text": "Surface",
                      "type": "text"
                    }
                  ],
                  "type": "paragraph"
                }
              ],
              "type": "tableHeader"
            },
            {
              "attrs": {
                "colspan": 1,
                "rowspan": 1
              },
              "content": [
                {
                  "content": [
                    {
                      "text": "Expected state",
                      "type": "text"
                    }
                  ],
                  "type": "paragraph"
                }
              ],
              "type": "tableHeader"
            },
            {
              "attrs": {
                "colspan": 1,
                "rowspan": 1
              },
              "content": [
                {
                  "content": [
                    {
                      "text": "Owner and date",
                      "type": "text"
                    }
                  ],
                  "type": "paragraph"
                }
              ],
              "type": "tableHeader"
            }
          ],
          "type": "tableRow"
        },
        {
          "content": [
            {
              "attrs": {
                "colspan": 1,
                "rowspan": 2
              },
              "content": [
                {
                  "content": [
                    {
                      "text": "Storage",
                      "type": "text"
                    }
                  ],
                  "type": "paragraph"
                }
              ],
              "type": "tableCell"
            },
            {
              "attrs": {
                "colspan": 1,
                "rowspan": 1
              },
              "content": [
                {
                  "content": [
                    {
                      "text": "Locally valid",
                      "type": "text"
                    }
                  ],
                  "type": "paragraph"
                }
              ],
              "type": "tableCell"
            },
            {
              "attrs": {
                "colspan": 1,
                "rowspan": 1
              },
              "content": [
                {
                  "content": [
                    {
                      "attrs": {
                        "id": "70121:6ec7fd06-929c-4771-add0-ec012097b466",
                        "text": "@Gerardo Jorge Villarroel González"
                      },
                      "type": "mention"
                    }
                  ],
                  "type": "paragraph"
                }
              ],
              "type": "tableCell"
            }
          ],
          "type": "tableRow"
        },
        {
          "content": [
            {
              "attrs": {
                "colspan": 1,
                "rowspan": 1
              },
              "content": [
                {
                  "content": [
                    {
                      "text": "Remotely rendered",
                      "type": "text"
                    }
                  ],
                  "type": "paragraph"
                }
              ],
              "type": "tableCell"
            },
            {
              "attrs": {
                "colspan": 1,
                "rowspan": 1
              },
              "content": [
                {
                  "content": [
                    {
                      "attrs": {
                        "timestamp": "1783900800000"
                      },
                      "type": "date"
                    }
                  ],
                  "type": "paragraph"
                }
              ],
              "type": "tableCell"
            }
          ],
          "type": "tableRow"
        }
      ],
      "type": "table"
    },
    {
      "attrs": {
        "level": 2
      },
      "content": [
        {
          "text": "Dates, mentions, emoji, and status",
          "type": "text"
        }
      ],
      "type": "heading"
    },
    {
      "content": [
        {
          "text": "Owner: ",
          "type": "text"
        },
        {
          "attrs": {
            "id": "70121:6ec7fd06-929c-4771-add0-ec012097b466",
            "text": "@Gerardo Jorge Villarroel González"
          },
          "type": "mention"
        },
        {
          "text": "; milestone: ",
          "type": "text"
        },
        {
          "attrs": {
            "timestamp": "1784505600000"
          },
          "type": "date"
        },
        {
          "text": "; reaction: ",
          "type": "text"
        },
        {
          "attrs": {
            "id": "1f642",
            "shortName": ":slight_smile:",
            "text": "🙂"
          },
          "type": "emoji"
        },
        {
          "text": ".",
          "type": "text"
        }
      ],
      "type": "paragraph"
    },
    {
      "content": [
        {
          "text": "Verification state: ",
          "type": "text"
        },
        {
          "attrs": {
            "color": "green",
            "localId": "2dde66d8-af4e-4afa-a9e2-00bdc5289b68",
            "style": "bold",
            "text": "NATIVE READY"
          },
          "type": "status"
        }
      ],
      "type": "paragraph"
    },
    {
      "attrs": {
        "level": 2
      },
      "content": [
        {
          "text": "One through five columns",
          "type": "text"
        }
      ],
      "type": "heading"
    },
    {
      "content": [
        {
          "attrs": {
            "width": 100.0
          },
          "content": [
            {
              "content": [
                {
                  "text": "Single-column layout cell",
                  "type": "text"
                }
              ],
              "type": "paragraph"
            }
          ],
          "type": "layoutColumn"
        }
      ],
      "type": "layoutSection"
    },
    {
      "content": [
        {
          "attrs": {
            "width": 50.0
          },
          "content": [
            {
              "content": [
                {
                  "text": "Two equal A",
                  "type": "text"
                }
              ],
              "type": "paragraph"
            }
          ],
          "type": "layoutColumn"
        },
        {
          "attrs": {
            "width": 50.0
          },
          "content": [
            {
              "content": [
                {
                  "text": "Two equal B",
                  "type": "text"
                }
              ],
              "type": "paragraph"
            }
          ],
          "type": "layoutColumn"
        }
      ],
      "type": "layoutSection"
    },
    {
      "content": [
        {
          "attrs": {
            "width": 33.33
          },
          "content": [
            {
              "content": [
                {
                  "text": "Left sidebar",
                  "type": "text"
                }
              ],
              "type": "paragraph"
            }
          ],
          "type": "layoutColumn"
        },
        {
          "attrs": {
            "width": 66.66
          },
          "content": [
            {
              "content": [
                {
                  "text": "Wide right content",
                  "type": "text"
                }
              ],
              "type": "paragraph"
            }
          ],
          "type": "layoutColumn"
        }
      ],
      "type": "layoutSection"
    },
    {
      "content": [
        {
          "attrs": {
            "width": 66.66
          },
          "content": [
            {
              "content": [
                {
                  "text": "Wide left content",
                  "type": "text"
                }
              ],
              "type": "paragraph"
            }
          ],
          "type": "layoutColumn"
        },
        {
          "attrs": {
            "width": 33.33
          },
          "content": [
            {
              "content": [
                {
                  "text": "Right sidebar",
                  "type": "text"
                }
              ],
              "type": "paragraph"
            }
          ],
          "type": "layoutColumn"
        }
      ],
      "type": "layoutSection"
    },
    {
      "content": [
        {
          "attrs": {
            "width": 33.33
          },
          "content": [
            {
              "content": [
                {
                  "text": "Three equal A",
                  "type": "text"
                }
              ],
              "type": "paragraph"
            }
          ],
          "type": "layoutColumn"
        },
        {
          "attrs": {
            "width": 33.33
          },
          "content": [
            {
              "content": [
                {
                  "text": "Three equal B",
                  "type": "text"
                }
              ],
              "type": "paragraph"
            }
          ],
          "type": "layoutColumn"
        },
        {
          "attrs": {
            "width": 33.33
          },
          "content": [
            {
              "content": [
                {
                  "text": "Three equal C",
                  "type": "text"
                }
              ],
              "type": "paragraph"
            }
          ],
          "type": "layoutColumn"
        }
      ],
      "type": "layoutSection"
    },
    {
      "content": [
        {
          "attrs": {
            "width": 25.0
          },
          "content": [
            {
              "content": [
                {
                  "text": "Three left sidebar",
                  "type": "text"
                }
              ],
              "type": "paragraph"
            }
          ],
          "type": "layoutColumn"
        },
        {
          "attrs": {
            "width": 50.0
          },
          "content": [
            {
              "content": [
                {
                  "text": "Three wide center",
                  "type": "text"
                }
              ],
              "type": "paragraph"
            }
          ],
          "type": "layoutColumn"
        },
        {
          "attrs": {
            "width": 25.0
          },
          "content": [
            {
              "content": [
                {
                  "text": "Three right sidebar",
                  "type": "text"
                }
              ],
              "type": "paragraph"
            }
          ],
          "type": "layoutColumn"
        }
      ],
      "type": "layoutSection"
    },
    {
      "content": [
        {
          "attrs": {
            "width": 25.0
          },
          "content": [
            {
              "content": [
                {
                  "text": "Four A",
                  "type": "text"
                }
              ],
              "type": "paragraph"
            }
          ],
          "type": "layoutColumn"
        },
        {
          "attrs": {
            "width": 25.0
          },
          "content": [
            {
              "content": [
                {
                  "text": "Four B",
                  "type": "text"
                }
              ],
              "type": "paragraph"
            }
          ],
          "type": "layoutColumn"
        },
        {
          "attrs": {
            "width": 25.0
          },
          "content": [
            {
              "content": [
                {
                  "text": "Four C",
                  "type": "text"
                }
              ],
              "type": "paragraph"
            }
          ],
          "type": "layoutColumn"
        },
        {
          "attrs": {
            "width": 25.0
          },
          "content": [
            {
              "content": [
                {
                  "text": "Four D",
                  "type": "text"
                }
              ],
              "type": "paragraph"
            }
          ],
          "type": "layoutColumn"
        }
      ],
      "type": "layoutSection"
    },
    {
      "content": [
        {
          "attrs": {
            "width": 20.0
          },
          "content": [
            {
              "content": [
                {
                  "text": "Five A",
                  "type": "text"
                }
              ],
              "type": "paragraph"
            }
          ],
          "type": "layoutColumn"
        },
        {
          "attrs": {
            "width": 20.0
          },
          "content": [
            {
              "content": [
                {
                  "text": "Five B",
                  "type": "text"
                }
              ],
              "type": "paragraph"
            }
          ],
          "type": "layoutColumn"
        },
        {
          "attrs": {
            "width": 20.0
          },
          "content": [
            {
              "content": [
                {
                  "text": "Five C",
                  "type": "text"
                }
              ],
              "type": "paragraph"
            }
          ],
          "type": "layoutColumn"
        },
        {
          "attrs": {
            "width": 20.0
          },
          "content": [
            {
              "content": [
                {
                  "text": "Five D",
                  "type": "text"
                }
              ],
              "type": "paragraph"
            }
          ],
          "type": "layoutColumn"
        },
        {
          "attrs": {
            "width": 20.0
          },
          "content": [
            {
              "content": [
                {
                  "text": "Five E",
                  "type": "text"
                }
              ],
              "type": "paragraph"
            }
          ],
          "type": "layoutColumn"
        }
      ],
      "type": "layoutSection"
    },
    {
      "attrs": {
        "level": 2
      },
      "content": [
        {
          "text": "Native editor acceptance complete",
          "type": "text"
        }
      ],
      "type": "heading"
    },
    {
      "content": [
        {
          "text": "All markers in this fixture are intentional and must remain visible after a no-op re-download and verification.",
          "type": "text"
        }
      ],
      "type": "paragraph"
    }
  ],
  "type": "doc",
  "version": 1
}
