{
  "_links": {
    "self": "/api/v2/pages/34504707/properties"
  },
  "meta": {
    "hasMore": false
  },
  "results": [
    {
      "id": "34504723",
      "key": "page-title-property-draft",
      "value": "{\"titleLayoutAlignment\":\"LEFT\",\"subtitle\":\"\",\"subtitleEnabled\":false,\"titlePropertyBylineEnabled\":false,\"titlePropertyEmojiEnabled\":false,\"headerImageLayout\":\"ABOVE\",\"headerImageStylingEnabled\":false}",
      "version": {
        "authorId": "70121:6ec7fd06-929c-4771-add0-ec012097b466",
        "createdAt": "2026-07-13T02:01:18.748Z",
        "message": "",
        "minorEdit": false,
        "number": 1
      }
    },
    {
      "id": "34504725",
      "key": "page-title-property-published",
      "value": "{\"titleLayoutAlignment\":\"LEFT\",\"subtitle\":\"\",\"subtitleEnabled\":false,\"titlePropertyBylineEnabled\":false,\"titlePropertyEmojiEnabled\":false,\"headerImageLayout\":\"ABOVE\",\"headerImageStylingEnabled\":false}",
      "version": {
        "authorId": "70121:6ec7fd06-929c-4771-add0-ec012097b466",
        "createdAt": "2026-07-13T02:01:18.757Z",
        "message": "",
        "minorEdit": false,
        "number": 1
      }
    }
  ]
}
